pyhackrf2/__init__.py
pyhackrf2/cinterface.py
pyhackrf2-1.0.3.dist-info/METADATA
pyhackrf2-1.0.3.dist-info/WHEEL
pyhackrf2-1.0.3.dist-info/top_level.txt
pyhackrf2-1.0.3.dist-info/RECORD
