Metadata-Version: 2.1
Name: pyhackrf2
Version: 1.0.3
Summary: Python bindings for libhackrf rewritten
Classifier: Topic :: Communications :: Ham Radio
Classifier: License :: OSI Approved :: MIT License
Classifier: Operating System :: OS Independent
Requires-Python: >=3
Requires-Dist: numpy (>=1.24)
